dustbunny/__init__.py
dustbunny/generate.py
dustbunny/perms.py
dustbunny/hyp/__init__.py
dustbunny/hyp/strategies.py
dustbunny/hyp/assets/adjectives.txt
dustbunny/hyp/assets/animals.txt
dustbunny/hyp/assets/first_names.txt
dustbunny/hyp/assets/last_names.txt
dustbunny/sqla/__init__.py
dustbunny-1.3.2.dist-info/LICENSE
dustbunny-1.3.2.dist-info/METADATA
dustbunny-1.3.2.dist-info/WHEEL
dustbunny-1.3.2.dist-info/top_level.txt
dustbunny-1.3.2.dist-info/RECORD
