Metadata-Version: 2.1
Name: dustbunny
Version: 1.3.2
Summary: Generate test records for sqlalchemy
Home-page: https://github.com/Teamworksapp/dustbunny
Author: Jefferson Heard
Author-email: jheard@teamworks.com
License: MIT
Keywords: pytest hypothesis sqlalchemy
Platform: UNKNOWN
Classifier: Development Status :: 3 - Alpha
Classifier: Intended Audience :: Developers
Classifier: Topic :: Software Development :: Testing
Classifier: License :: OSI Approved :: MIT License
Classifier: Programming Language :: Python :: 3
Classifier: Programming Language :: Python :: 3.2
Classifier: Programming Language :: Python :: 3.3
Classifier: Programming Language :: Python :: 3.4
Classifier: Programming Language :: Python :: 3.5
Classifier: Programming Language :: Python :: 3.6
Requires-Dist: hypothesis
Requires-Dist: numpy
Requires-Dist: sqlalchemy
Requires-Dist: pytz
